gl_api_requester/GLAPIRequester.py
gl_api_requester/__init__.py
gl_api_requester/dto/DTO.py
gl_api_requester/dto/request/alliance/GetAllianceDTO.py
gl_api_requester/dto/request/player/GetPlayerByIdDTO.py
gl_api_requester/dto/request/player/GetPlayerByNameDTO.py
gl_api_requester/dto/response/alliance/AllianceDTO.py
gl_api_requester/dto/response/alliance/AllianceEmblemDTO.py
gl_api_requester/dto/response/alliance/AlliancePlayerDTO.py
gl_api_requester/dto/response/alliance/AllianceWarpointsDTO.py
gl_api_requester/dto/response/leaderboard/LeaderboardRivalsWonPlayerDTO.py
gl_api_requester/dto/response/leaderboard/LeaderboardWarpointsPlayerDTO.py
gl_api_requester/dto/response/leaderboard/LeaderboardXpFromAttackPlayerDTO.py
gl_api_requester/dto/response/planet/PlanetDTO.py
gl_api_requester/dto/response/player/PlayerDTO.py
gl_api_requester/dto/response/player/PlayerStatsDTO.py
gl_api_requester/dto/response/status/ServerStatusDTO.py
gl_api_requester/exception/APIErrorException.py
gl_api_requester-1.0.1.dist-info/LICENSE
gl_api_requester-1.0.1.dist-info/METADATA
gl_api_requester-1.0.1.dist-info/WHEEL
gl_api_requester-1.0.1.dist-info/top_level.txt
gl_api_requester-1.0.1.dist-info/RECORD
