Metadata-Version: 2.1
Name: gl-api-requester
Version: 1.0.1
Summary: The Galaxy Life API requester.
Author-email: FL-GL <franceleadergl@gmail.com>
Project-URL: Homepage, https://github.com/France-Leader-Galaxy-Life/GL-Python-API-Requester
Classifier: Programming Language :: Python :: 3
Classifier: License :: OSI Approved :: MIT License
Classifier: Operating System :: OS Independent
Requires-Python: >=3.7
License-File: LICENSE
Requires-Dist: dacite
Requires-Dist: requests
